coordinator/__init__.py
coordinator-1.0.0b1.dist-info/LICENSE
coordinator-1.0.0b1.dist-info/METADATA
coordinator-1.0.0b1.dist-info/WHEEL
coordinator-1.0.0b1.dist-info/top_level.txt
coordinator-1.0.0b1.dist-info/RECORD
