Metadata-Version: 2.1
Name: coordinator
Version: 1.0.0b1
Summary: An experimental Python hook-based task runner.
Home-page: https://github.com/juniorrubyist/coordinator
Author: Joseph Geis
Author-email: juniorrubyist@gmail.com
License: UNKNOWN
Platform: UNKNOWN
Classifier: Programming Language :: Python :: 3
Classifier: License :: OSI Approved :: MIT License
Classifier: Operating System :: OS Independent
Requires-Python: >=3.6
Requires-Dist: huey
Requires-Dist: gevent
